{
  "font": "Iosevka",
  "font-size": "12",
  "font-size-in-dpi": "18",
  "border-half-size": "2",
  "border-size": "4",

  "base00-hex": "32302f",
  "base01-hex": "3c3836",
  "base02-hex": "504945",
  "base03-hex": "665c54",
  "base04-hex": "bdae93",
  "base05-hex": "d5c4a1",
  "base06-hex": "ebdbb2",
  "base07-hex": "fbf1c7",
  "base08-hex": "fb4934",
  "base09-hex": "fe8019",
  "base0A-hex": "fabd2f",
  "base0B-hex": "b8bb26",
  "base0C-hex": "8ec07c",
  "base0D-hex": "83a598",
  "base0E-hex": "d3869b",
  "base0F-hex": "d65d0e"
}
